vvlib/__init__.py
vvlib/vvlib_functions.py
vvlib-0.4.1.dist-info/METADATA
vvlib-0.4.1.dist-info/WHEEL
vvlib-0.4.1.dist-info/RECORD
