Metadata-Version: 2.3
Name: vvlib
Version: 0.4.1
Summary: A collection of random (mostly useless) functions
Author: Vojtech Velebny
Author-email: velebnyvo@gymla.cz
Requires-Python: >=3.11
Classifier: Programming Language :: Python :: 3
Classifier: Programming Language :: Python :: 3.11
Classifier: Programming Language :: Python :: 3.12
Classifier: Programming Language :: Python :: 3.13
